yaz_pyotp/__init__.py
yaz_pyotp/client.py
yaz_pyotp/settings.py
yaz_pyotp/core/base.py
yaz_pyotp/core/factory.py
yaz_pyotp/core/hasher.py
yaz_pyotp/core/otp.py
yaz_pyotp/core/types.py
yaz_pyotp-0.0.1.dist-info/METADATA
yaz_pyotp-0.0.1.dist-info/WHEEL
yaz_pyotp-0.0.1.dist-info/licenses/LICENSE
yaz_pyotp-0.0.1.dist-info/RECORD
